odoo/addons/mgmtsystem_nonconformity_maintenance/README.rst
odoo/addons/mgmtsystem_nonconformity_maintenance/__init__.py
odoo/addons/mgmtsystem_nonconformity_maintenance/__manifest__.py
odoo/addons/mgmtsystem_nonconformity_maintenance/i18n/it.po
odoo/addons/mgmtsystem_nonconformity_maintenance/i18n/mgmtsystem_nonconformity_maintenance.pot
odoo/addons/mgmtsystem_nonconformity_maintenance/i18n/pt_BR.po
odoo/addons/mgmtsystem_nonconformity_maintenance/models/__init__.py
odoo/addons/mgmtsystem_nonconformity_maintenance/models/maintenance_request.py
odoo/addons/mgmtsystem_nonconformity_maintenance/models/mgmtsystem_nonconformity.py
odoo/addons/mgmtsystem_nonconformity_maintenance/readme/CONTRIBUTORS.rst
odoo/addons/mgmtsystem_nonconformity_maintenance/readme/DESCRIPTION.rst
odoo/addons/mgmtsystem_nonconformity_maintenance/readme/USAGE.rst
odoo/addons/mgmtsystem_nonconformity_maintenance/static/description/icon.png
odoo/addons/mgmtsystem_nonconformity_maintenance/static/description/index.html
odoo/addons/mgmtsystem_nonconformity_maintenance/views/mgmtsystem_nonconformity.xml
odoo_addon_mgmtsystem_nonconformity_maintenance-16.0.1.0.0.1.dist-info/METADATA
odoo_addon_mgmtsystem_nonconformity_maintenance-16.0.1.0.0.1.dist-info/WHEEL
odoo_addon_mgmtsystem_nonconformity_maintenance-16.0.1.0.0.1.dist-info/top_level.txt
odoo_addon_mgmtsystem_nonconformity_maintenance-16.0.1.0.0.1.dist-info/RECORD
